LICENSE
README.md
pytest/test.py
.vscode/launch.json
dna_mutation_quantifier/__init__.py
dna_mutation_quantifier/analysis.py
dna_mutation_quantifier/calibration.py
dna_mutation_quantifier/core.py
dna_mutation_quantifier/ratio_to_substitution_matrix.tsv
dna_mutation_quantifier/run.py
dna_mutation_quantifier/sanger.py
dna_mutation_quantifier/version.py
xeniorn_dna_mutation_quantifier-0.0.7.dist-info/METADATA
xeniorn_dna_mutation_quantifier-0.0.7.dist-info/WHEEL
xeniorn_dna_mutation_quantifier-0.0.7.dist-info/licenses/LICENSE
xeniorn_dna_mutation_quantifier-0.0.7.dist-info/RECORD
