Metadata-Version: 2.1
Name: xeniorn-dna_mutation_quantifier
Version: 0.0.7
Summary: Quantification of Sanger traces
Project-URL: Homepage, https://github.com/xeniorn/DnaMutationQuantifier
Project-URL: Bug Tracker, https://github.com/xeniorn/DnaMutationQuantifier/issues
Author-email: Juraj Ahel <juraj.ahel@gmail.com>
License-File: LICENSE
Classifier: License :: OSI Approved :: MIT License
Classifier: Operating System :: OS Independent
Classifier: Programming Language :: Python :: 3
Requires-Python: >=3.7
Requires-Dist: biopython>=1.81
Requires-Dist: matplotlib>=3.7.1
Requires-Dist: numpy>=1.23.5
Requires-Dist: pandas>=1.5.3
Requires-Dist: scipy>=1.11
